Metadata-Version: 2.1
Name: remote-exec
Version: 1.11.0
Summary: A CLI to sync codebases and execute commands remotely
Home-page: https://github.com/shirshanka/remote
Author: Shirshanka Das
License: BSD-2-CLAUSE
Platform: UNKNOWN
Classifier: Development Status :: 5 - Production/Stable
Classifier: Programming Language :: Python
Classifier: Programming Language :: Python :: 3
Classifier: Programming Language :: Python :: 3 :: Only
Classifier: Programming Language :: Python :: 3.6
Classifier: Programming Language :: Python :: 3.7
Classifier: Programming Language :: Python :: 3.8
Classifier: Intended Audience :: Developers
Classifier: Intended Audience :: Information Technology
Classifier: Intended Audience :: System Administrators
Classifier: License :: OSI Approved
Classifier: License :: OSI Approved :: BSD License
Classifier: Operating System :: Unix
Classifier: Operating System :: POSIX :: Linux
Classifier: Environment :: Console
Classifier: Environment :: MacOS X
Classifier: Topic :: Software Development
Requires-Python: >=3.6
Requires-Dist: click (>=7.1.1)
Requires-Dist: toml (>=0.10.0)
Requires-Dist: pydantic (>=1.5.1)
Requires-Dist: watchdog (>=0.10.3)
Requires-Dist: dataclasses ; python_version <= "3.6"
